PyQSF/PyQSF.py
PyQSF/__init__.py
PyQSF-1.0.0.dist-info/METADATA
PyQSF-1.0.0.dist-info/WHEEL
PyQSF-1.0.0.dist-info/top_level.txt
PyQSF-1.0.0.dist-info/RECORD
