Metadata-Version: 2.1
Name: PyQSF
Version: 1.0.0
Summary: Python Quelert System Files
Author: Georgy2008
Author-email: zadvornow2008@gmail.com
Classifier: Programming Language :: Python :: 3
Classifier: License :: OSI Approved :: MIT License
Classifier: Operating System :: OS Independent
Requires-Python: >=3.6
